edwh_migrate/__about__.py
edwh_migrate/__init__.py
edwh_migrate/constants.py
edwh_migrate/helpers.py
edwh_migrate/migrate.py
edwh_migrate/postgres.py
edwh_migrate/py.typed
edwh_migrate/view_migration_manager.py
edwh_migrate-1.1.2.dist-info/METADATA
edwh_migrate-1.1.2.dist-info/WHEEL
edwh_migrate-1.1.2.dist-info/entry_points.txt
edwh_migrate-1.1.2.dist-info/RECORD
