Metadata-Version: 2.4
Name: edwh-migrate
Version: 1.1.2
Summary: Helps migrating database schema changes using pydal. 
Project-URL: Documentation, https://github.com/educationwarehouse/migrate#readme
Project-URL: Issues, https://github.com/educationwarehouse/migrate/issues
Project-URL: Source, https://github.com/educationwarehouse/migrate
Author-email: Remco <remco@educationwarehouse.nl>, Robin <robin@educationwarehouse.nl>
Keywords: database-migration,migrate,postgresql,pydal,schema-change
Classifier: Development Status :: 4 - Beta
Classifier: Programming Language :: Python
Classifier: Programming Language :: Python :: 3.10
Classifier: Programming Language :: Python :: 3.11
Classifier: Programming Language :: Python :: 3.12
Classifier: Programming Language :: Python :: 3.13
Classifier: Programming Language :: Python :: Implementation :: CPython
Classifier: Programming Language :: Python :: Implementation :: PyPy
Requires-Python: >=3.10
Requires-Dist: configuraptor>=1.23
Requires-Dist: legacy-cgi; python_version >= '3.13'
Requires-Dist: plumbum
Requires-Dist: pydal>=20221110.1
Requires-Dist: python-dotenv
Requires-Dist: tabulate
Provides-Extra: dev
Requires-Dist: black; extra == 'dev'
Requires-Dist: contextlib-chdir; extra == 'dev'
Requires-Dist: hatch; extra == 'dev'
Requires-Dist: isort; extra == 'dev'
Requires-Dist: psycopg2-binary; extra == 'dev'
Requires-Dist: pytest; extra == 'dev'
Requires-Dist: pytest-cov; extra == 'dev'
Requires-Dist: python-semantic-release<8; extra == 'dev'
Requires-Dist: redis; extra == 'dev'
Requires-Dist: sqlalchemy-utils; extra == 'dev'
Requires-Dist: testcontainers; extra == 'dev'
Requires-Dist: typedal; extra == 'dev'
Provides-Extra: full
Requires-Dist: psycopg2-binary; extra == 'full'
Requires-Dist: redis; extra == 'full'
